{
    "LCustomEntity": {
        "Readings": [
            {
                "ID": 1000,
                "FinalizedBy": 1,
                "IsFinalized": "true",
                "ObjectTypeID": 1,
                "CalculationTypeID": 760118,
                "DataInputMethodID": 760137,
                "ReadingEntityID": 15408,
                "ObjectID": 95583236,
                "ModifiedBy": 34365,
                "CreatedBy": 34365,
                "ModifiedOn": "2023-11-21 12:34:49",
                "CreatedOn": "2023-11-21 12:34:49",
                "ReadingNumber": 1,
                "ReadingID": 1000,
                "ReadingTime": "00:00:00",
                "ReadingDate": "2023-07-24",
                "Comments": null,
                "AuthorityLevelID": 760111,
                "IsDeleted": "False",
                "CreatedTimestamp": "2023-08-03 23:36:45",
                "ModifiedTimestamp": "2022-08-03 23:36:45"
            },
            {
                "ID": 1001,
                "FinalizedBy": 1,
                "IsFinalized": "true",
                "ObjectTypeID": 1,
                "CalculationTypeID": 760118,
                "DataInputMethodID": 760137,
                "ReadingEntityID": 15408,
                "ObjectID": 95583236,
                "ModifiedBy": 34365,
                "CreatedBy": 34365,
                "ModifiedOn": "2023-11-21 12:34:49",
                "CreatedOn": "2023-11-21 12:34:49",
                "ReadingNumber": 2,
                "ReadingID": 1001,
                "ReadingTime": "00:00:00",
                "ReadingDate": "2023-07-25",
                "Comments": null,
                "AuthorityLevelID": 760111,
                "IsDeleted": "False",
                "CreatedTimestamp": "2023-08-03 23:36:45",
                "ModifiedTimestamp": "2022-08-03 23:36:45"
            },
            {
                "ID": 1002,
                "FinalizedBy": 1,
                "IsFinalized": "true",
                "ObjectTypeID": 1,
                "CalculationTypeID": 760118,
                "DataInputMethodID": 760137,
                "ReadingEntityID": 15408,
                "ObjectID": 95583236,
                "ModifiedBy": 34365,
                "CreatedBy": 34365,
                "ModifiedOn": "2023-11-21 12:34:49",
                "CreatedOn": "2023-11-21 12:34:49",
                "ReadingNumber": 3,
                "ReadingID": 1002,
                "ReadingTime": "00:00:00",
                "ReadingDate": "2023-07-26",
                "Comments": null,
                "AuthorityLevelID": 760111,
                "IsDeleted": "False",
                "CreatedTimestamp": "2023-08-03 23:36:45",
                "ModifiedTimestamp": "2022-08-03 23:36:45"
            },
            {
                "ID": 1003,
                "FinalizedBy": 1,
                "IsFinalized": "true",
                "ObjectTypeID": 1,
                "CalculationTypeID": 760118,
                "DataInputMethodID": 760137,
                "ReadingEntityID": 15408,
                "ObjectID": 95583236,
                "ModifiedBy": 34365,
                "CreatedBy": 34365,
                "ModifiedOn": "2023-11-21 12:34:49",
                "CreatedOn": "2023-11-21 12:34:49",
                "ReadingNumber": 4,
                "ReadingID": 1003,
                "ReadingTime": "00:00:00",
                "ReadingDate": "2023-07-27",
                "Comments": null,
                "AuthorityLevelID": 760111,
                "IsDeleted": "False",
                "CreatedTimestamp": "2023-08-03 23:36:45",
                "ModifiedTimestamp": "2022-08-03 23:36:45"
            },
            {
                "ID": 1004,
                "FinalizedBy": 1,
                "IsFinalized": "true",
                "ObjectTypeID": 1,
                "CalculationTypeID": 760118,
                "DataInputMethodID": 760137,
                "ReadingEntityID": 15408,
                "ObjectID": 95583236,
                "ModifiedBy": 34365,
                "CreatedBy": 34365,
                "ModifiedOn": "2023-11-21 12:34:49",
                "CreatedOn": "2023-11-21 12:34:49",
                "ReadingNumber": 5,
                "ReadingID": 1004,
                "ReadingTime": "00:00:00",
                "ReadingDate": "2023-07-28",
                "Comments": null,
                "AuthorityLevelID": 760111,
                "IsDeleted": "False",
                "CreatedTimestamp": "2023-08-03 23:36:45",
                "ModifiedTimestamp": "2022-08-03 23:36:45"
            },
            {
                "ID": 1005,
                "FinalizedBy": 1,
                "IsFinalized": "true",
                "ObjectTypeID": 1,
                "CalculationTypeID": 760118,
                "DataInputMethodID": 760137,
                "ReadingEntityID": 15408,
                "ObjectID": 95583236,
                "ModifiedBy": 34365,
                "CreatedBy": 34365,
                "ModifiedOn": "2023-11-21 12:34:49",
                "CreatedOn": "2023-11-21 12:34:49",
                "ReadingNumber": 6,
                "ReadingID": 1005,
                "ReadingTime": "00:00:00",
                "ReadingDate": "2023-07-29",
                "Comments": null,
                "AuthorityLevelID": 760111,
                "IsDeleted": "False",
                "CreatedTimestamp": "2023-08-03 23:36:45",
                "ModifiedTimestamp": "2022-08-03 23:36:45"
            },
            {
                "ID": 1006,
                "FinalizedBy": 1,
                "IsFinalized": "true",
                "ObjectTypeID": 1,
                "CalculationTypeID": 760118,
                "DataInputMethodID": 760137,
                "ReadingEntityID": 15408,
                "ObjectID": 95583236,
                "ModifiedBy": 34365,
                "CreatedBy": 34365,
                "ModifiedOn": "2023-11-21 12:34:49",
                "CreatedOn": "2023-11-21 12:34:49",
                "ReadingNumber": 7,
                "ReadingID": 1006,
                "ReadingTime": "00:00:00",
                "ReadingDate": "2023-07-30",
                "Comments": null,
                "AuthorityLevelID": 760111,
                "IsDeleted": "False",
                "CreatedTimestamp": "2023-08-03 23:36:45",
                "ModifiedTimestamp": "2022-08-03 23:36:45"
            }
        ],
        "custo": {
            "dts": [],
            "strs": [],
            "decs": [
                {
                    "ID": 2,
                    "attId": 263005,
                    "ReadingID": 1000,
                    "v": "47.43"
                },
                {
                    "ID": 4,
                    "attId": 263005,
                    "ReadingID": 1000,
                    "v": "263"
                },
                {
                    "ID": 6,
                    "attId": 263005,
                    "ReadingID": 1000,
                    "v": "0"
                },
                {
                    "ID": 8,
                    "attId": 263005,
                    "ReadingID": 1000,
                    "v": "239.75"
                },
                {
                    "ID": 12,
                    "attId": 263005,
                    "ReadingID": 1001,
                    "v": "66.96"
                },
                {
                    "ID": 14,
                    "attId": 263005,
                    "ReadingID": 1001,
                    "v": "267"
                },
                {
                    "ID": 16,
                    "attId": 263005,
                    "ReadingID": 1001,
                    "v": "369.74"
                },
                {
                    "ID": 18,
                    "attId": 263005,
                    "ReadingID": 1001,
                    "v": "229.75"
                },
                {
                    "ID": 22,
                    "attId": 263005,
                    "ReadingID": 1002,
                    "v": "44.64"
                },
                {
                    "ID": 24,
                    "attId": 263005,
                    "ReadingID": 1002,
                    "v": "235"
                },
                {
                    "ID": 26,
                    "attId": 263005,
                    "ReadingID": 1002,
                    "v": "0"
                },
                {
                    "ID": 28,
                    "attId": 263005,
                    "ReadingID": 1002,
                    "v": "232.5"
                },
                {
                    "ID": 32,
                    "attId": 263005,
                    "ReadingID": 1003,
                    "v": "44.64"
                },
                {
                    "ID": 34,
                    "attId": 263005,
                    "ReadingID": 1003,
                    "v": "241"
                },
                {
                    "ID": 36,
                    "attId": 263005,
                    "ReadingID": 1003,
                    "v": "0"
                },
                {
                    "ID": 38,
                    "attId": 263005,
                    "ReadingID": 1003,
                    "v": "225.25"
                },
                {
                    "ID": 42,
                    "attId": 263005,
                    "ReadingID": 1004,
                    "v": "47.43"
                },
                {
                    "ID": 44,
                    "attId": 263005,
                    "ReadingID": 1004,
                    "v": "265"
                },
                {
                    "ID": 46,
                    "attId": 263005,
                    "ReadingID": 1004,
                    "v": "0"
                },
                {
                    "ID": 48,
                    "attId": 263005,
                    "ReadingID": 1004,
                    "v": "230.5"
                },
                {
                    "ID": 52,
                    "attId": 263005,
                    "ReadingID": 1005,
                    "v": "44.64"
                },
                {
                    "ID": 54,
                    "attId": 263005,
                    "ReadingID": 1005,
                    "v": "122"
                },
                {
                    "ID": 56,
                    "attId": 263005,
                    "ReadingID": 1005,
                    "v": "0"
                },
                {
                    "ID": 58,
                    "attId": 263005,
                    "ReadingID": 1005,
                    "v": "243"
                },
                {
                    "ID": 62,
                    "attId": 263005,
                    "ReadingID": 1006,
                    "v": "53.01"
                },
                {
                    "ID": 64,
                    "attId": 263005,
                    "ReadingID": 1006,
                    "v": "126"
                },
                {
                    "ID": 66,
                    "attId": 263005,
                    "ReadingID": 1006,
                    "v": "0"
                },
                {
                    "ID": 68,
                    "attId": 263005,
                    "ReadingID": 1006,
                    "v": "215"
                }
            ],
            "ints": [
                {
                    "ID": 3,
                    "attId": 263002,
                    "ReadingID": 1000,
                    "v": "760011"
                },
                {
                    "ID": 3456,
                    "attId": 263003,
                    "ReadingID": 1000,
                    "v": "760096"
                },
                {
                    "ID": 5,
                    "attId": 263002,
                    "ReadingID": 1000,
                    "v": "760010"
                },
                {
                    "ID": 7,
                    "attId": 263003,
                    "ReadingID": 1000,
                    "v": "760098"
                },
                {
                    "ID": 9,
                    "attId": 263002,
                    "ReadingID": 1000,
                    "v": "760012"
                },
                {
                    "ID": 13,
                    "attId": 263002,
                    "ReadingID": 1001,
                    "v": "760011"
                },
                {
                    "ID": 15,
                    "attId": 263002,
                    "ReadingID": 1001,
                    "v": "760010"
                },
                {
                    "ID": 17,
                    "attId": 263003,
                    "ReadingID": 1001,
                    "v": "760098"
                },
                {
                    "ID": 19,
                    "attId": 263002,
                    "ReadingID": 1001,
                    "v": "760012"
                },
                {
                    "ID": 23,
                    "attId": 263002,
                    "ReadingID": 1002,
                    "v": "760011"
                },
                {
                    "ID": 25,
                    "attId": 263002,
                    "ReadingID": 1002,
                    "v": "760010"
                },
                {
                    "ID": 27,
                    "attId": 263003,
                    "ReadingID": 1002,
                    "v": "760098"
                },
                {
                    "ID": 29,
                    "attId": 263002,
                    "ReadingID": 1002,
                    "v": "760012"
                },
                {
                    "ID": 33,
                    "attId": 263002,
                    "ReadingID": 1003,
                    "v": "760011"
                },
                {
                    "ID": 35,
                    "attId": 263002,
                    "ReadingID": 1003,
                    "v": "760010"
                },
                {
                    "ID": 37,
                    "attId": 263003,
                    "ReadingID": 1003,
                    "v": "760098"
                },
                {
                    "ID": 39,
                    "attId": 263002,
                    "ReadingID": 1003,
                    "v": "760012"
                },
                {
                    "ID": 43,
                    "attId": 263002,
                    "ReadingID": 1004,
                    "v": "760011"
                },
                {
                    "ID": 45,
                    "attId": 263002,
                    "ReadingID": 1004,
                    "v": "760010"
                },
                {
                    "ID": 47,
                    "attId": 263003,
                    "ReadingID": 1004,
                    "v": "760098"
                },
                {
                    "ID": 49,
                    "attId": 263002,
                    "ReadingID": 1004,
                    "v": "760012"
                },
                {
                    "ID": 53,
                    "attId": 263002,
                    "ReadingID": 1005,
                    "v": "760011"
                },
                {
                    "ID": 55,
                    "attId": 263002,
                    "ReadingID": 1005,
                    "v": "760010"
                },
                {
                    "ID": 57,
                    "attId": 263003,
                    "ReadingID": 1005,
                    "v": "760098"
                },
                {
                    "ID": 59,
                    "attId": 263002,
                    "ReadingID": 1005,
                    "v": "760012"
                },
                {
                    "ID": 63,
                    "attId": 263002,
                    "ReadingID": 1006,
                    "v": "760011"
                },
                {
                    "ID": 65,
                    "attId": 263002,
                    "ReadingID": 1006,
                    "v": "760010"
                },
                {
                    "ID": 67,
                    "attId": 263003,
                    "ReadingID": 1006,
                    "v": "760098"
                },
                {
                    "ID": 69,
                    "attId": 263002,
                    "ReadingID": 1006,
                    "v": "760012"
                }
            ],
            "txts": [],
            "bits": []
        }
    },
    "LLACTMeterReading": null,
    "LWellReading": null,
    "LDualPhaseOilWaterTankReading": null,
    "LSinglePhaseWaterTankReading": null,
    "LTankRunTicket": null,
    "LMeterLACTTicket": null,
    "LEquipmentReading": null,
    "LDigitalMeterGASReading": null,
    "LDigitalMeterOilWaterReading": null,
    "LSinglePhaseOilTankReading": null,
    "LWellTestReading": null,
    "LOdometerMeterReading": null,
    "LOrficeHRCoefficientMeterReading": null,
    "LOrficeMeterReading": null,
    "LWaterTicket": null,
    "UseXID": false,
    "ColumnsToUpdate": null,
    "ValidationFormula": null
}